{
  "hero_id": "152",
  "passive": {
    "name": "凍てつく魂",
    "description": "戦闘を離脱すると450（450+魔法攻撃の58%）のシールドを獲得し、敵がシールドに物理ダメージを与えると、その敵に寒冷効果を付与する。シールド消失時、付近の敵に400（400+魔法攻撃の75%）の魔法ダメージと寒冷効果を付与する。3回目の通常攻撃が強化通常攻撃になり、3本の氷柱を放ち180（180+魔法攻撃の36%）の魔法ダメージを与える。氷柱はそれぞれ100%の通常攻撃特殊効果となる。アクティブスキルと強化通常攻撃が命中すると寒冷効果が付与され、ターゲットの移動速度を25～50%、攻撃速度を25～50%減少させる。この効果は2秒かけて次第に減少する。"
  },
  "skill1": {
    "name": "朽ちた氷晶",
    "tags": [
      "移動速度減少",
      "ダメージ",
      "視界"
    ],
    "cooldown": "CD : 5秒",
    "description": "氷の結晶を指定位置に放ち、範囲内の敵に350（350+魔法攻撃の50%）の魔法ダメージを与えて寒冷効果を付与する。同時に範囲内及び命中した敵の視界を2秒間獲得する。"
  },
  "skill2": {
    "name": "氷の監獄",
    "tags": [
      "CC",
      "移動速度減少",
      "ダメージ"
    ],
    "cooldown": "CD : 9秒",
    "description": "指定位置に氷の力を召喚し、一定時間経過後に範囲内の敵に250（250+魔法攻撃の50%）の魔法ダメージを与え、更に2.5秒間凍結効果を付与する。凍結させた敵に追加で150（150+魔法攻撃の20%）の魔法ダメージを与える。"
  },
  "skill3": {
    "name": "冬の訪れ",
    "tags": [
      "移動速度減少",
      "ダメージ"
    ],
    "cooldown": "CD : 35秒",
    "description": "指定位置に5秒間持続するブリザードを召喚し、0.5秒ごとに範囲内の敵に200（200+魔法攻撃の35%）の魔法ダメージを与えて寒冷効果を付与する。ブリザードを召喚するとパッシブスキルのシールドを再度獲得できる。"
  },
  "status_text": "最大HP: 3206\n最大MP: 640\n物理攻撃: 166\n魔法攻撃: 10 (0+10)\n物理防御: 150 | 20%\n魔法防御: 75 | 11.1%\n移動速度: 365\n物理防御貫通: 0 | 0%\n魔法防御貫通: 0 | 0%\n攻撃速度ボーナス: 5%\nクリティカル率: 0%\nクリティカル効果: 200%\n物理ライフスティール: 0%\n魔法ライフスティール: 0%\nクールダウン短縮: 0%\n攻撃範囲: 遠距離\n耐性: 0%\n5秒ごとのHP回復: 44\n5秒ごとのMP回復: 16"
}