{
  "zh": [
    {
      "id": "P",
      "name": "天雷引",
      "description": "[冷却值：0 消耗：0]\n司空震的普通攻击造成140（+30%物理攻击）（+25%法术攻击）法术伤害。近距离会触发近战攻击，攻击间隔降低。普攻获得1点天雷之力，上限6点。达到上限时引动天雷，获得一次额外释放基础技能的机会。释放基础技能后，获得强化普攻，对大范围内敌人造成300(+25%法术攻击)法术伤害。远程强化普攻锁定目标以外单位受到75%伤害，不触发法球效果。",
      "icon": "/images/skills/537_0.png"
    },
    {
      "id": "Q",
      "name": "奔雷疾",
      "description": "[冷却值：10/9.6/9.2/8.8/8.4/8 消耗：0]\n司空震化身奔雷向前疾行，对路径上敌人造成180/216/252/288/324/360(+20%法术攻击)法术伤害并获得210/235/260/285/310/335(+10%法术攻击)点护盾，持续2秒。",
      "icon": "/images/skills/537_1.png"
    },
    {
      "id": "W",
      "name": "狂雷击",
      "description": "[冷却值：13/12.6/12.2/11.8/11.4/11 消耗：0]\n司空震向前释放出一道狂雷之力，达到最大射程，或触碰到单位短暂延迟后爆炸，造成击退和250/300/350/400/450/500(+30%法术攻击)法术伤害。离司空震距离越近的单位被击退得越远。",
      "icon": "/images/skills/537_2.png"
    },
    {
      "id": "E",
      "name": "雷霆万钧",
      "description": "[冷却值：70/60/50 消耗：0]\n司空震升入空中，化身为雷霆之王。 变身过程持续1.5秒，期间获得霸体，增加30%移动速度，无视地形阻挡，并让五个雷鼓依次随机轰击附近敌人（优先英雄）。每次雷击造成80/100/120(+4%法术攻击)法术伤害，并使司空震获得1点天雷之力和180/210/240(+10%法术攻击)点护盾，持续1秒。落地时对附近敌人造成360/540/720(+35%法术伤害)法术伤害。 变身持续10秒，期间普攻改为获得2点天雷之力，远程普攻会产生雷电链，在多个敌人间弹射，造成100/150/200(+10%法术攻击)法术伤害。强化普攻的范围增加。",
      "icon": "/images/skills/537_3.png"
    },
    {
      "id": "R",
      "name": "",
      "description": "[冷却值： 消耗：]\n",
      "icon": "/images/skills/537_4.png"
    }
  ],
  "ja": [
    {
      "id": "P",
      "name": "天雷音",
      "description": "【冷却値：0 消費量：0】\nSikong Zhen の通常攻撃は 140 (+30% 物理攻撃) (+25% 魔法攻撃) の魔法ダメージを与えます。近接攻撃が近距離で発動し、攻撃間隔が短くなります。基本攻撃は雷パワーを 1 ポイント獲得しますが、最大値は 6 ポイントです。上限に達すると雷が発生し、基本スキルの解放チャンスが追加されます。基本スキルを解放すると基本攻撃力が強化され、広範囲の敵に300（+25％魔法攻撃力）の魔法ダメージを与えます。遠隔強化通常攻撃の対象以外のユニットは75%のダメージを受け、魔球の効果は発動しない。",
      "icon": "/images/skills/537_0.png"
    },
    {
      "id": "Q",
      "name": "ベン・レイ・ジー",
      "description": "【冷却値：10/9.6/9.2/8.8/8.4/8 消費量：0】\nSikong Zhen が走る雷に変身して前方に突進し、道上の敵に 180/216/252/288/324/360 (+20% 魔法攻撃) の魔法ダメージを与え、2 秒間 210/235/260/285/310/335 (+10% 魔法攻撃) のシールド ポイントを獲得します。",
      "icon": "/images/skills/537_1.png"
    },
    {
      "id": "W",
      "name": "狂った落雷",
      "description": "【冷却値：13/12.6/12.2/11.8/11.4/11 消費量：0】\nSikong Zhen は前方に雷の爆風を放ち、最大射程に達するかユニットに触れると少し遅れて爆発し、ノックバックと 250/300/350/400/450/500 (+30% 呪文攻撃) の呪文ダメージを引き起こします。 Sikong Zhen に近いユニットはさらに遠くに押し戻されます。",
      "icon": "/images/skills/537_2.png"
    },
    {
      "id": "E",
      "name": "雷",
      "description": "【冷却値：70/60/50 消費量：0】\nシコン・ジェンは空中に上がり、雷王に変身しました。変身プロセスは 1.5 秒間続き、その間に彼は優位性を獲得し、移動速度が 30% 増加し、地形の障害物を無視し、5 つのサンダードラムが近くの敵を順番にランダムに砲撃できるようになります (ヒーロー優先)。各落雷は 80/100/120 (+4% 魔法攻撃) の魔法ダメージを与え、Sikong Zhen は 1 ポイントの雷パワーと 180/210/240 (+10% 魔法攻撃) のシールド ポイントを獲得します。これは 1 秒間持続します。着地すると、近くの敵に 360/540/720 (+35% 魔法ダメージ) の魔法ダメージを与えます。変身は10秒間続きます。この間、通常攻撃で雷威力が2ポイント増加する。遠距離通常攻撃は稲妻の連鎖を生成し、複数の敵の間で跳ね返り、100/150/200 (+10% 魔法攻撃) の魔法ダメージを与えます。強化された通常攻撃の範囲が増加しました。",
      "icon": "/images/skills/537_3.png"
    },
    {
      "id": "R",
      "name": "",
      "description": "【冷却価：消費量：】",
      "icon": "/images/skills/537_4.png"
    }
  ]
}